writeas_view_extractor/__init__.py
writeas_view_extractor/main.py
writeas_view_extractor-1.0.1.dist-info/entry_points.txt
writeas_view_extractor-1.0.1.dist-info/WHEEL
writeas_view_extractor-1.0.1.dist-info/METADATA
writeas_view_extractor-1.0.1.dist-info/RECORD
